colorGenerator/__init__.py
colorGenerator/colorGenerator.py
colorGenerator-1.2.1.dist-info/LICENSE
colorGenerator-1.2.1.dist-info/METADATA
colorGenerator-1.2.1.dist-info/WHEEL
colorGenerator-1.2.1.dist-info/top_level.txt
colorGenerator-1.2.1.dist-info/RECORD
