Metadata-Version: 2.1
Name: colorGenerator
Version: 1.2.1
Summary: This package help you find complementary colors
Home-page: https://github.com/tttienthinh/colorGenerator.git
Author: tttienthinh
Author-email: tranthuongtienthinh@gmail.com
License: UNKNOWN
Project-URL: Download, https://pypi.org/project/colorGenerator/
Project-URL: Source Code, https://github.com/tttienthinh/colorGenerator.git
Project-URL: Documentation, https://colorgenerator.readthedocs.io
Project-URL: Bug Tracker, https://github.com/tttienthinh/colorGenerator/issues
Platform: UNKNOWN
Classifier: Programming Language :: Python :: 3
Classifier: License :: OSI Approved :: MIT License
Classifier: Operating System :: OS Independent
Requires-Python: >=3.6
